doi2pdf/__init__.py
doi2pdf/main.py
doi2pdf-0.1.3.dist-info/LICENSE
doi2pdf-0.1.3.dist-info/METADATA
doi2pdf-0.1.3.dist-info/WHEEL
doi2pdf-0.1.3.dist-info/entry_points.txt
doi2pdf-0.1.3.dist-info/RECORD
