Metadata-Version: 2.1
Name: doi2pdf
Version: 0.1.3
Summary: Retrieve research paper PDF from DOI, name or URL of the research paper
License: MIT
Author: croumegous
Author-email: cyril.roumegous@gmail.com
Requires-Python: >=3.7,<4.0
Classifier: License :: OSI Approved :: MIT License
Classifier: Programming Language :: Python :: 3
Classifier: Programming Language :: Python :: 3.7
Classifier: Programming Language :: Python :: 3.8
Classifier: Programming Language :: Python :: 3.9
Classifier: Programming Language :: Python :: 3.10
Classifier: Programming Language :: Python :: 3.11
Requires-Dist: beautifulsoup4 (>=4.11.1,<5.0.0)
Requires-Dist: requests (>=2.28.1,<3.0.0)
